libsne/Constantes.py
libsne/__init__.py
libsne/libsne.py
libsne-0.1.0a10.dist-info/DESCRIPTION.rst
libsne-0.1.0a10.dist-info/METADATA
libsne-0.1.0a10.dist-info/RECORD
libsne-0.1.0a10.dist-info/WHEEL
libsne-0.1.0a10.dist-info/entry_points.txt
libsne-0.1.0a10.dist-info/metadata.json
libsne-0.1.0a10.dist-info/top_level.txt
