Metadata-Version: 2.0
Name: libsne
Version: 0.1.0a10
Summary: Python library for SNE synchronous exchanges
Home-page: http://trac.interne.cliss21.org/libsne/
Author: Cliss XXI
Author-email: contact@cliss21.org
License: GNU AGPL-3
Keywords: libsne
Platform: UNKNOWN
Classifier: Development Status :: 3 - Alpha
Classifier: Intended Audience :: Developers
Classifier: License :: OSI Approved :: GNU Affero General Public License v3
Classifier: Natural Language :: French
Classifier: Programming Language :: Python :: 2
Classifier: Programming Language :: Python :: 2.6
Classifier: Programming Language :: Python :: 2.7
Classifier: Programming Language :: Python :: 3
Classifier: Programming Language :: Python :: 3.4
Classifier: Programming Language :: Python :: 3.5
Requires-Dist: jinja2
Requires-Dist: lxml
Requires-Dist: six
